MANIFEST.in
README.rst
setup.cfg
setup.py
versioneer.py
multi_locus_analysis/__init__.py
multi_locus_analysis/_version.py
multi_locus_analysis/analytical.py
multi_locus_analysis/dataframes.py
multi_locus_analysis/fitting.py
multi_locus_analysis/util.py
multi_locus_analysis/vvcf_table.csv
multi_locus_analysis.egg-info/PKG-INFO
multi_locus_analysis.egg-info/SOURCES.txt
multi_locus_analysis.egg-info/dependency_links.txt
multi_locus_analysis.egg-info/requires.txt
multi_locus_analysis.egg-info/top_level.txt
multi_locus_analysis/examples/__init__.py
multi_locus_analysis/examples/burgess/__init__.py
multi_locus_analysis/examples/burgess/analysis.py
multi_locus_analysis/examples/burgess/msds.py
multi_locus_analysis/examples/burgess/plotting.py
multi_locus_analysis/examples/burgess/simulation.py
multi_locus_analysis/examples/burgess/styles.py
multi_locus_analysis/examples/burgess/workflow.py