Metadata-Version: 1.1
Name: multi-locus-analysis
Version: 0.1.0
Summary: Utilities for analyzing particle trajectories
Home-page: https://github.com/brunobeltran/multi_locus_analysis
Author: Bruno Beltran
Author-email: brunobeltran0@gmail.com
License: MIT
Keywords: microscopy diffusion scientific
Platform: UNKNOWN
Classifier: Development Status :: 2 - Pre-Alpha
Classifier: Intended Audience :: Developers
Classifier: Intended Audience :: Science/Research
Classifier: License :: OSI Approved :: MIT License
Classifier: Topic :: Utilities
